agent_frame/__init__.py
agent_frame/agent_base.py
agent_frame/gym_runner.py
agent_frame-0.3.0.dist-info/METADATA
agent_frame-0.3.0.dist-info/WHEEL
agent_frame-0.3.0.dist-info/top_level.txt
agent_frame-0.3.0.dist-info/RECORD
