Metadata-Version: 2.1
Name: agent-frame
Version: 0.3.0
Summary: A framework to make creating AI agents easier
Home-page: http://www.ryanjames.io
Author: Ryan McCauley
Author-email: ryanmccauley211@gmail.com
License: UNKNOWN
Platform: UNKNOWN
